[
  {
    "line": 1,
    "elements": [
      {
        "before": [
          {
            "result": {
              "duration": 22019070500,
              "status": "passed"
            },
            "match": {
              "location": "Hooks.setup()"
            }
          }
        ],
        "line": 25,
        "name": "Search for multiple products",
        "description": "",
        "id": "funcionality;search-for-multiple-products;;2",
        "after": [
          {
            "result": {
              "duration": 11774696900,
              "status": "passed"
            },
            "match": {
              "location": "Hooks.teardown()"
            }
          }
        ],
        "type": "scenario",
        "keyword": "Scenario Outline",
        "steps": [
          {
            "result": {
              "duration": 1029800300,
              "status": "passed"
            },
            "line": 20,
            "name": "User is on Argos homepage",
            "match": {
              "location": "Homepage_Accountbutton.user_is_on_Argos_homepage()"
            },
            "keyword": "Given "
          },
          {
            "result": {
              "duration": 12022930000,
              "status": "passed"
            },
            "line": 21,
            "name": "user search for \"nike\"",
            "match": {
              "arguments": [
                {
                  "val": "nike",
                  "offset": 17
                }
              ],
              "location": "Homepage_ScenarioOutlineSteps.user_search_for(String)"
            },
            "matchedColumns": [
              0
            ],
            "keyword": "When "
          },
          {
            "result": {
              "duration": 34000,
              "status": "passed"
            },
            "line": 22,
            "name": "user should be able to search multiple products",
            "match": {
              "location": "Homepage_ScenarioOutlineSteps.user_should_be_able_to_search_multiple_products()"
            },
            "keyword": "Then "
          }
        ],
        "tags": [
          {
            "line": 17,
            "name": "@MultipleInput"
          }
        ]
      },
      {
        "before": [
          {
            "result": {
              "duration": 21242861900,
              "status": "passed"
            },
            "match": {
              "location": "Hooks.setup()"
            }
          }
        ],
        "line": 26,
        "name": "Search for multiple products",
        "description": "",
        "id": "funcionality;search-for-multiple-products;;3",
        "after": [
          {
            "result": {
              "duration": 12441213900,
              "status": "passed"
            },
            "match": {
              "location": "Hooks.teardown()"
            }
          }
        ],
        "type": "scenario",
        "keyword": "Scenario Outline",
        "steps": [
          {
            "result": {
              "duration": 434200,
              "status": "passed"
            },
            "line": 20,
            "name": "User is on Argos homepage",
            "match": {
              "location": "Homepage_Accountbutton.user_is_on_Argos_homepage()"
            },
            "keyword": "Given "
          },
          {
            "result": {
              "duration": 19940245400,
              "status": "passed"
            },
            "line": 21,
            "name": "user search for \"puma\"",
            "match": {
              "arguments": [
                {
                  "val": "puma",
                  "offset": 17
                }
              ],
              "location": "Homepage_ScenarioOutlineSteps.user_search_for(String)"
            },
            "matchedColumns": [
              0
            ],
            "keyword": "When "
          },
          {
            "result": {
              "duration": 34200,
              "status": "passed"
            },
            "line": 22,
            "name": "user should be able to search multiple products",
            "match": {
              "location": "Homepage_ScenarioOutlineSteps.user_should_be_able_to_search_multiple_products()"
            },
            "keyword": "Then "
          }
        ],
        "tags": [
          {
            "line": 17,
            "name": "@MultipleInput"
          }
        ]
      }
    ],
    "name": "Funcionality",
    "description": "",
    "id": "funcionality",
    "keyword": "Feature",
    "uri": "C:/Users/shagu/IdeaProjects/BDDFramework/BDDFramework/src/test/Resourses/Homepage.feature"
  }
]